pranerpack/__init__.py
pranerpack/base.py
pranerpack-0.0.1.dist-info/METADATA
pranerpack-0.0.1.dist-info/WHEEL
pranerpack-0.0.1.dist-info/top_level.txt
pranerpack-0.0.1.dist-info/RECORD
